HISTORY.rst
LICENSE
MANIFEST.in
README.rst
setup.cfg
setup.py
docs/Makefile
docs/conf.py
docs/history.rst
docs/index.rst
docs/make.bat
docs/readme.rst
instant2fa/__init__.py
instant2fa/api_requestor.py
instant2fa/errors.py
instant2fa/jsonapi.py
instant2fa/resources.py
instant2fa.egg-info/PKG-INFO
instant2fa.egg-info/SOURCES.txt
instant2fa.egg-info/dependency_links.txt
instant2fa.egg-info/not-zip-safe
instant2fa.egg-info/requires.txt
instant2fa.egg-info/top_level.txt
tests/test_instant2fa.py