Metadata-Version: 1.0
Name: instant2fa
Version: 1.0.0
Summary: Instant2FA Python bindings.
Home-page: https://github.com/clef/instant2fa-python
Author: Grace Wong
Author-email: grace@getclef.com
License: ISCL
Keywords: instant2fa
Platform: UNKNOWN
